{"nodes": [{"id": "shared_httproute_pulse_route", "label": "pulse-route HTTPRoute", "file_type": "code", "source_file": "k8s/shared/httproute.yaml"}], "edges": [{"source": "shared_httproute_pulse_route", "target": "shared_gateway_pulse_gateway", "relation": "references", "confidence": "EXTRACTED", "confidence_score": 1.0, "source_file": "k8s/shared/httproute.yaml"}, {"source": "shared_httproute_pulse_route", "target": "user_service_service_user_service", "relation": "references", "confidence": "EXTRACTED", "confidence_score": 1.0, "source_file": "k8s/shared/httproute.yaml"}], "hyperedges": []}